traceease/TraceEase.py
traceease/__init__.py
traceease/errors.json
traceease/errors.py
traceease/themes.json
traceease/utils.py
traceease-0.1.0.dist-info/licenses/LICENSE
traceease-0.1.0.dist-info/METADATA
traceease-0.1.0.dist-info/WHEEL
traceease-0.1.0.dist-info/top_level.txt
traceease-0.1.0.dist-info/RECORD
