Metadata-Version: 2.4
Name: TraceEase
Version: 0.1.0
Summary: Beginner-friendly error tracing for Python.
Home-page: https://github.com/00-Masterpiece/TraceEase
Author: Jaden Gregory
Author-email: jaden.andru@gmail.com
License: Proprietary
Classifier: Programming Language :: Python :: 3
Classifier: Operating System :: OS Independent
Classifier: License :: Other/Proprietary License
Requires-Python: >=3.7
License-File: LICENSE
Requires-Dist: rich>=13.0
Dynamic: author
Dynamic: author-email
Dynamic: classifier
Dynamic: home-page
Dynamic: license
Dynamic: license-file
Dynamic: requires-dist
Dynamic: requires-python
Dynamic: summary
